seda/__init__.py
seda/__main__.py
seda/app.py
seda/client.py
seda/config.py
seda/decorators.py
seda/exceptions.py
seda/logging.py
seda/policies.py
seda/py.typed
seda/run.py
seda/session.py
seda/tasks.py
seda/types.py
seda/utils.py
seda/cli/__init__.py
seda/cli/callbacks.py
seda/cli/cmd.py
seda/cli/deploy.py
seda/cli/main.py
seda/cli/options.py
seda/cli/remove.py
seda-0.0.6.dist-info/METADATA
seda-0.0.6.dist-info/WHEEL
seda-0.0.6.dist-info/entry_points.txt
seda-0.0.6.dist-info/licenses/LICENSE
seda-0.0.6.dist-info/RECORD
