Metadata-Version: 2.1
Name: seda
Version: 0.0.6
Summary: A Python toolkit to build Serverless Event-Driven Applications on AWS.
Project-URL: homepage, https://github.com/mongkok/seda
Project-URL: repository, https://github.com/mongkok/seda
Project-URL: documentation, https://seda.domake.io
Project-URL: changelog, https://seda.domake.io/changelog/
Author-email: Dani <dani@domake.io>
License-Expression: BSD-3-Clause
License-File: LICENSE
Keywords: aws,event-driven,scheduler,serverless
Classifier: Development Status :: 1 - Planning
Classifier: Environment :: Web Environment
Classifier: Intended Audience :: Developers
Classifier: License :: OSI Approved :: BSD License
Classifier: Operating System :: OS Independent
Classifier: Programming Language :: Python
Classifier: Programming Language :: Python :: 3
Classifier: Programming Language :: Python :: 3.7
Classifier: Programming Language :: Python :: 3.8
Classifier: Programming Language :: Python :: 3.9
Classifier: Programming Language :: Python :: 3.10
Classifier: Programming Language :: Python :: 3.11
Classifier: Topic :: Internet
Classifier: Topic :: Internet :: WWW/HTTP
Classifier: Topic :: Internet :: WWW/HTTP :: HTTP Servers
Classifier: Topic :: Software Development
Classifier: Topic :: Software Development :: Libraries
Classifier: Topic :: Software Development :: Libraries :: Python Modules
Classifier: Topic :: Utilities
Classifier: Typing :: Typed
Requires-Python: >=3.7
Requires-Dist: anyio>=3.4.0
Requires-Dist: botocore>=1.29.7
Requires-Dist: click>=7.0
Requires-Dist: typing-extensions; python_version < '3.11'
Provides-Extra: asgi
Requires-Dist: mangum; extra == 'asgi'
Provides-Extra: doc
Requires-Dist: markdown-include; extra == 'doc'
Requires-Dist: mkdocs; extra == 'doc'
Requires-Dist: mkdocs-material; extra == 'doc'
Requires-Dist: mkdocstrings[python]; extra == 'doc'
Provides-Extra: test
Requires-Dist: black; extra == 'test'
Requires-Dist: codecov; extra == 'test'
Requires-Dist: flake8; extra == 'test'
Requires-Dist: isort; extra == 'test'
Requires-Dist: mypy; extra == 'test'
Requires-Dist: pytest; extra == 'test'
Requires-Dist: pytest-cov; extra == 'test'
